itstepweather.py
itstepweather-0.1.0.dist-info/WHEEL
itstepweather-0.1.0.dist-info/METADATA
itstepweather-0.1.0.dist-info/RECORD
