Metadata-Version: 2.1
Name: itstepweather
Version: 0.1.0
Summary: Simple weather module for ITStep students
Author: Eugene
Author-email: coulderapid@gmail.com
Requires-Python: >=3.6,<4.0
Classifier: Programming Language :: Python :: 3
Classifier: Programming Language :: Python :: 3.6
Classifier: Programming Language :: Python :: 3.7
Classifier: Programming Language :: Python :: 3.8
Classifier: Programming Language :: Python :: 3.9
